py2vyu/__init__.py
py2vyu/py2vyu.py
tests/__init__.py
tests/test_pyvyu.py
py2vyu-0.1.0.dist-info/LICENSE
py2vyu-0.1.0.dist-info/METADATA
py2vyu-0.1.0.dist-info/WHEEL
py2vyu-0.1.0.dist-info/top_level.txt
py2vyu-0.1.0.dist-info/RECORD
