Metadata-Version: 2.1
Name: py2vyu
Version: 0.1.0
Summary: Python2 backport of pyvyu
Home-page: UNKNOWN
Author: Shohan Hasan
Author-email: shohan.hasan@nyu.edu
License: UNKNOWN
Platform: UNKNOWN
Requires-Python: >=2.7
